kybatis/__init__.py
kybatis/connector.py
kybatis/mapper.py
kybatis/types_.py
kybatis-0.0.2.dist-info/LICENSE
kybatis-0.0.2.dist-info/METADATA
kybatis-0.0.2.dist-info/WHEEL
kybatis-0.0.2.dist-info/top_level.txt
kybatis-0.0.2.dist-info/RECORD
