Metadata-Version: 2.1
Name: kybatis
Version: 0.0.2
Summary: minimal db utility in mybatis style
Author: kyon
Author-email: originky2@gmail.com
License: Apache-2.0
Classifier: Programming Language :: Python :: 3.11
Requires-Python: >=3.10
License-File: LICENSE
Requires-Dist: pydantic (>=2.10)
Requires-Dist: oracledb (>=2.5)
Requires-Dist: mysql-connector-python (>=9.2)
